buildbot_tags_section_plugin/VERSION
buildbot_tags_section_plugin/__init__.py
buildbot_tags_section_plugin/static/scripts.js
buildbot_tags_section_plugin/static/scripts.js.map
buildbot_tags_section_plugin/static/styles.css
buildbot_tags_section_plugin/static/styles.css.map
buildbot_tags_section_plugin-2020.8.20.dist-info/METADATA
buildbot_tags_section_plugin-2020.8.20.dist-info/WHEEL
buildbot_tags_section_plugin-2020.8.20.dist-info/entry_points.txt
buildbot_tags_section_plugin-2020.8.20.dist-info/top_level.txt
buildbot_tags_section_plugin-2020.8.20.dist-info/RECORD
