Metadata-Version: 2.1
Name: buildbot-tags-section-plugin
Version: 2020.8.20
Summary: Add builders filters menu section
Home-page: https://github.com/vlasov-evgeny/buildbot-tags-section
Author: Evgeny Vlasov
Author-email: evgeny.vlasov@fruct.org
License: UNKNOWN
Platform: UNKNOWN
Classifier: License :: OSI Approved :: GNU General Public License v2 (GPLv2)
